<?xml version="1.0" encoding="utf-8"?>
<clothing-items>
 <clothing>
  <id>
   773300665
  </id>
  <name>
   Adidas Jacket K-7291
  </name>
  <category>
   Jacket
  </category>
  <size>
   XL
  </size>
  <color>
   Желтый
  </color>
  <material>
   Шерсть
  </material>
  <price>
   139090
  </price>
  <rating>
   2.16
  </rating>
  <reviews>
   408061
  </reviews>
  <new>
   -
  </new>
  <exclusive>
   yes
  </exclusive>
  <sporty>
   yes
  </sporty>
 </clothing>
 <clothing>
  <id>
   326032818
  </id>
  <name>
   Lacoste Blouse L-3702
  </name>
  <category>
   Blouse
  </category>
  <size>
   XL
  </size>
  <color>
   Оранжевый
  </color>
  <material>
   Полиэстер
  </material>
  <price>
   928641
  </price>
  <rating>
   3.26
  </rating>
  <reviews>
   869690
  </reviews>
  <new>
   -
  </new>
  <exclusive>
   no
  </exclusive>
 </clothing>
 <clothing>
  <id>
   946006316
  </id>
  <name>
   Brooks Jacket N-8271
  </name>
  <category>
   Jacket
  </category>
  <size>
   L
  </size>
  <color>
   Синий
  </color>
  <material>
   Хлопок
  </material>
  <price>
   823712
  </price>
  <rating>
   4.05
  </rating>
  <reviews>
   399305
  </reviews>
  <new>
   +
  </new>
  <exclusive>
   yes
  </exclusive>
 </clothing>
 <clothing>
  <id>
   641063132
  </id>
  <name>
   Addidas Skirt Z-7869
  </name>
  <category>
   Skirt
  </category>
  <size>
   M
  </size>
  <color>
   Голубой
  </color>
  <material>
   Вискоза
  </material>
  <price>
   507045
  </price>
  <rating>
   2.56
  </rating>
  <reviews>
   809927
  </reviews>
  <new>
   -
  </new>
  <sporty>
   no
  </sporty>
 </clothing>
 <clothing>
  <id>
   223937391
  </id>
  <name>
   Fila Jeans A-4320
  </name>
  <category>
   Jeans
  </category>
  <size>
   M
  </size>
  <color>
   Красный
  </color>
  <material>
   Кожа
  </material>
  <price>
   138301
  </price>
  <rating>
   1.88
  </rating>
  <reviews>
   389305
  </reviews>
  <new>
   -
  </new>
  <exclusive>
   yes
  </exclusive>
 </clothing>
 <clothing>
  <id>
   318190340
  </id>
  <name>
   Fila Handbags H-8954
  </name>
  <category>
   Handbags
  </category>
  <size>
   S
  </size>
  <color>
   Голубой
  </color>
  <material>
   Лен
  </material>
  <price>
   322330
  </price>
  <rating>
   4.06
  </rating>
  <reviews>
   84207
  </reviews>
  <new>
   -
  </new>
 </clothing>
 <clothing>
  <id>
   559396030
  </id>
  <name>
   Fila Dress W-3849
  </name>
  <category>
   Dress
  </category>
  <size>
   L
  </size>
  <color>
   Синий
  </color>
  <material>
   Шерсть
  </material>
  <price>
   911854
  </price>
  <rating>
   4.37
  </rating>
  <reviews>
   677483
  </reviews>
  <sporty>
   no
  </sporty>
 </clothing>
 <clothing>
  <id>
   885992392
  </id>
  <name>
   Ellesse Pants X-1936
  </name>
  <category>
   Pants
  </category>
  <size>
   L
  </size>
  <color>
   Зеленый
  </color>
  <material>
   Шелк
  </material>
  <price>
   569778
  </price>
  <rating>
   3.43
  </rating>
  <reviews>
   723712
  </reviews>
  <sporty>
   no
  </sporty>
 </clothing>
 <clothing>
  <id>
   753955189
  </id>
  <name>
   Asics Socks T-7746
  </name>
  <category>
   Socks
  </category>
  <size>
   XL
  </size>
  <color>
   Голубой
  </color>
  <material>
   Нейлон
  </material>
  <price>
   221456
  </price>
  <rating>
   2.91
  </rating>
  <reviews>
   153316
  </reviews>
  <new>
   +
  </new>
 </clothing>
 <clothing>
  <id>
   415126554
  </id>
  <name>
   Lacoste Socks I-4691
  </name>
  <category>
   Socks
  </category>
  <size>
   XXL
  </size>
  <color>
   Оранжевый
  </color>
  <material>
   Шелк
  </material>
  <price>
   646216
  </price>
  <rating>
   1.96
  </rating>
  <reviews>
   526829
  </reviews>
  <new>
   -
  </new>
  <exclusive>
   yes
  </exclusive>
 </clothing>
 <clothing>
  <id>
   390117375
  </id>
  <name>
   Addidas Pants C-7346
  </name>
  <category>
   Pants
  </category>
  <size>
   M
  </size>
  <color>
   Зеленый
  </color>
  <material>
   Вискоза
  </material>
  <price>
   430501
  </price>
  <rating>
   4.05
  </rating>
  <reviews>
   632727
  </reviews>
  <new>
   +
  </new>
  <exclusive>
   no
  </exclusive>
  <sporty>
   no
  </sporty>
 </clothing>
 <clothing>
  <id>
   793048174
  </id>
  <name>
   Nike Blouse F-4387
  </name>
  <category>
   Blouse
  </category>
  <size>
   L
  </size>
  <color>
   Фиолетовый
  </color>
  <material>
   Шерсть
  </material>
  <price>
   586773
  </price>
  <rating>
   4.78
  </rating>
  <reviews>
   284116
  </reviews>
  <new>
   +
  </new>
  <exclusive>
   yes
  </exclusive>
  <sporty>
   no
  </sporty>
 </clothing>
 <clothing>
  <id>
   246916797
  </id>
  <name>
   Ellesse Blouse K-5346
  </name>
  <category>
   Blouse
  </category>
  <size>
   S
  </size>
  <color>
   Фиолетовый
  </color>
  <material>
   Полиэстер
  </material>
  <price>
   208641
  </price>
  <rating>
   3.13
  </rating>
  <reviews>
   961929
  </reviews>
  <new>
   -
  </new>
  <exclusive>
   no
  </exclusive>
  <sporty>
   yes
  </sporty>
 </clothing>
 <clothing>
  <id>
   344375917
  </id>
  <name>
   Fila Skirt M-4230
  </name>
  <category>
   Skirt
  </category>
  <size>
   L
  </size>
  <color>
   Синий
  </color>
  <material>
   Вискоза
  </material>
  <price>
   225832
  </price>
  <rating>
   3.42
  </rating>
  <reviews>
   31437
  </reviews>
  <new>
   -
  </new>
  <exclusive>
   no
  </exclusive>
  <sporty>
   no
  </sporty>
 </clothing>
 <clothing>
  <id>
   914981498
  </id>
  <name>
   Brooks Pants I-5040
  </name>
  <category>
   Pants
  </category>
  <size>
   XL
  </size>
  <color>
   Зеленый
  </color>
  <material>
   Хлопок
  </material>
  <price>
   923354
  </price>
  <rating>
   4.88
  </rating>
  <reviews>
   645392
  </reviews>
  <new>
   -
  </new>
  <exclusive>
   yes
  </exclusive>
 </clothing>
 <clothing>
  <id>
   268234547
  </id>
  <name>
   Adidas Socks G-8700
  </name>
  <category>
   Socks
  </category>
  <size>
   S
  </size>
  <color>
   Красный
  </color>
  <material>
   Шерсть
  </material>
  <price>
   402584
  </price>
  <rating>
   1.4
  </rating>
  <reviews>
   955917
  </reviews>
  <new>
   -
  </new>
  <exclusive>
   no
  </exclusive>
  <sporty>
   no
  </sporty>
 </clothing>
 <clothing>
  <id>
   555615246
  </id>
  <name>
   Brooks Socks H-8365
  </name>
  <category>
   Socks
  </category>
  <size>
   S
  </size>
  <color>
   Красный
  </color>
  <material>
   Хлопок
  </material>
  <price>
   822442
  </price>
  <rating>
   1.66
  </rating>
  <reviews>
   827756
  </reviews>
  <sporty>
   no
  </sporty>
 </clothing>
 <clothing>
  <id>
   578150392
  </id>
  <name>
   Addidas Skirt O-9344
  </name>
  <category>
   Skirt
  </category>
  <size>
   XXL
  </size>
  <color>
   Синий
  </color>
  <material>
   Шелк
  </material>
  <price>
   706832
  </price>
  <rating>
   1.25
  </rating>
  <reviews>
   459798
  </reviews>
  <new>
   -
  </new>
  <exclusive>
   no
  </exclusive>
  <sporty>
   yes
  </sporty>
 </clothing>
 <clothing>
  <id>
   860725096
  </id>
  <name>
   Under Armour Blouse V-7193
  </name>
  <category>
   Blouse
  </category>
  <size>
   XXL
  </size>
  <color>
   Красный
  </color>
  <material>
   Полиэстер
  </material>
  <price>
   643333
  </price>
  <rating>
   2.94
  </rating>
  <reviews>
   625987
  </reviews>
  <new>
   +
  </new>
  <exclusive>
   no
  </exclusive>
  <sporty>
   no
  </sporty>
 </clothing>
 <clothing>
  <id>
   723039781
  </id>
  <name>
   Ellesse Jacket X-7708
  </name>
  <category>
   Jacket
  </category>
  <size>
   XXL
  </size>
  <color>
   Оранжевый
  </color>
  <material>
   Шерсть
  </material>
  <price>
   304955
  </price>
  <rating>
   1.37
  </rating>
  <reviews>
   482522
  </reviews>
  <new>
   +
  </new>
  <exclusive>
   no
  </exclusive>
  <sporty>
   yes
  </sporty>
 </clothing>
 <clothing>
  <id>
   512988349
  </id>
  <name>
   PleinSport Pants M-1746
  </name>
  <category>
   Pants
  </category>
  <size>
   XXL
  </size>
  <color>
   Красный
  </color>
  <material>
   Лен
  </material>
  <price>
   575014
  </price>
  <rating>
   1.81
  </rating>
  <reviews>
   502774
  </reviews>
  <exclusive>
   no
  </exclusive>
 </clothing>
 <clothing>
  <id>
   303045020
  </id>
  <name>
   Fila Sweater I-1868
  </name>
  <category>
   Sweater
  </category>
  <size>
   XXL
  </size>
  <color>
   Оранжевый
  </color>
  <material>
   Шелк
  </material>
  <price>
   972474
  </price>
  <rating>
   3.82
  </rating>
  <reviews>
   499968
  </reviews>
  <sporty>
   yes
  </sporty>
 </clothing>
 <clothing>
  <id>
   447307201
  </id>
  <name>
   Fila Belts B-3780
  </name>
  <category>
   Belts
  </category>
  <size>
   XXL
  </size>
  <color>
   Красный
  </color>
  <material>
   Кожа
  </material>
  <price>
   325322
  </price>
  <rating>
   3.21
  </rating>
  <reviews>
   541900
  </reviews>
  <new>
   +
  </new>
 </clothing>
 <clothing>
  <id>
   427678750
  </id>
  <name>
   New Balance Blouse Z-8618
  </name>
  <category>
   Blouse
  </category>
  <size>
   M
  </size>
  <color>
   Синий
  </color>
  <material>
   Вискоза
  </material>
  <price>
   411665
  </price>
  <rating>
   2.88
  </rating>
  <reviews>
   599305
  </reviews>
  <new>
   +
  </new>
  <exclusive>
   no
  </exclusive>
  <sporty>
   no
  </sporty>
 </clothing>
 <clothing>
  <id>
   117823770
  </id>
  <name>
   PleinSport Socks J-9552
  </name>
  <category>
   Socks
  </category>
  <size>
   S
  </size>
  <color>
   Желтый
  </color>
  <material>
   Вискоза
  </material>
  <price>
   932745
  </price>
  <rating>
   3.97
  </rating>
  <reviews>
   416144
  </reviews>
  <new>
   +
  </new>
  <exclusive>
   yes
  </exclusive>
 </clothing>
 <clothing>
  <id>
   542757360
  </id>
  <name>
   New Balance Shoes G-1770
  </name>
  <category>
   Shoes
  </category>
  <size>
   S
  </size>
  <color>
   Голубой
  </color>
  <material>
   Нейлон
  </material>
  <price>
   268081
  </price>
  <rating>
   1.59
  </rating>
  <reviews>
   202577
  </reviews>
  <new>
   +
  </new>
 </clothing>
 <clothing>
  <id>
   614647310
  </id>
  <name>
   Converse Shirt C-7437
  </name>
  <category>
   Shirt
  </category>
  <size>
   S
  </size>
  <color>
   Фиолетовый
  </color>
  <material>
   Вискоза
  </material>
  <price>
   938170
  </price>
  <rating>
   1.67
  </rating>
  <reviews>
   294769
  </reviews>
  <new>
   +
  </new>
  <exclusive>
   yes
  </exclusive>
 </clothing>
 <clothing>
  <id>
   418009537
  </id>
  <name>
   Addidas Hat V-4136
  </name>
  <category>
   Hat
  </category>
  <size>
   XXL
  </size>
  <color>
   Голубой
  </color>
  <material>
   Полиэстер
  </material>
  <price>
   593808
  </price>
  <rating>
   2.79
  </rating>
  <reviews>
   459958
  </reviews>
  <new>
   +
  </new>
  <exclusive>
   no
  </exclusive>
 </clothing>
 <clothing>
  <id>
   951456433
  </id>
  <name>
   PleinSport Shirt F-6316
  </name>
  <category>
   Shirt
  </category>
  <size>
   M
  </size>
  <color>
   Желтый
  </color>
  <material>
   Шелк
  </material>
  <price>
   261639
  </price>
  <rating>
   2.97
  </rating>
  <reviews>
   348787
  </reviews>
  <exclusive>
   yes
  </exclusive>
  <sporty>
   yes
  </sporty>
 </clothing>
 <clothing>
  <id>
   891804184
  </id>
  <name>
   Lacoste Gloves O-6408
  </name>
  <category>
   Gloves
  </category>
  <size>
   S
  </size>
  <color>
   Фиолетовый
  </color>
  <material>
   Полиэстер
  </material>
  <price>
   880943
  </price>
  <rating>
   2.78
  </rating>
  <reviews>
   798051
  </reviews>
  <new>
   -
  </new>
 </clothing>
 <clothing>
  <id>
   798071407
  </id>
  <name>
   PleinSport Handbags Q-4527
  </name>
  <category>
   Handbags
  </category>
  <size>
   L
  </size>
  <color>
   Зеленый
  </color>
  <material>
   Кожа
  </material>
  <price>
   343023
  </price>
  <rating>
   1.85
  </rating>
  <reviews>
   902685
  </reviews>
  <new>
   -
  </new>
  <sporty>
   no
  </sporty>
 </clothing>
 <clothing>
  <id>
   316305150
  </id>
  <name>
   DC Hat R-1268
  </name>
  <category>
   Hat
  </category>
  <size>
   XL
  </size>
  <color>
   Фиолетовый
  </color>
  <material>
   Кожа
  </material>
  <price>
   397031
  </price>
  <rating>
   4.25
  </rating>
  <reviews>
   135312
  </reviews>
  <new>
   -
  </new>
  <exclusive>
   yes
  </exclusive>
 </clothing>
 <clothing>
  <id>
   701523211
  </id>
  <name>
   Ellesse Pants W-1435
  </name>
  <category>
   Pants
  </category>
  <size>
   S
  </size>
  <color>
   Желтый
  </color>
  <material>
   Вискоза
  </material>
  <price>
   150122
  </price>
  <rating>
   3.29
  </rating>
  <reviews>
   339008
  </reviews>
  <new>
   +
  </new>
  <exclusive>
   yes
  </exclusive>
 </clothing>
 <clothing>
  <id>
   924250269
  </id>
  <name>
   Nike Hat M-8338
  </name>
  <category>
   Hat
  </category>
  <size>
   M
  </size>
  <color>
   Голубой
  </color>
  <material>
   Вискоза
  </material>
  <price>
   641279
  </price>
  <rating>
   1.38
  </rating>
  <reviews>
   285296
  </reviews>
  <new>
   -
  </new>
  <exclusive>
   no
  </exclusive>
  <sporty>
   no
  </sporty>
 </clothing>
 <clothing>
  <id>
   293132735
  </id>
  <name>
   Adidas Shoes G-3342
  </name>
  <category>
   Shoes
  </category>
  <size>
   XXL
  </size>
  <color>
   Голубой
  </color>
  <material>
   Шерсть
  </material>
  <price>
   849139
  </price>
  <rating>
   3.69
  </rating>
  <reviews>
   451195
  </reviews>
  <exclusive>
   yes
  </exclusive>
 </clothing>
 <clothing>
  <id>
   177663999
  </id>
  <name>
   Vans Socks Z-4165
  </name>
  <category>
   Socks
  </category>
  <size>
   XL
  </size>
  <color>
   Красный
  </color>
  <material>
   Нейлон
  </material>
  <price>
   945287
  </price>
  <rating>
   3.48
  </rating>
  <reviews>
   205040
  </reviews>
  <new>
   -
  </new>
  <exclusive>
   no
  </exclusive>
 </clothing>
 <clothing>
  <id>
   984417343
  </id>
  <name>
   Under Armour Jacket E-3356
  </name>
  <category>
   Jacket
  </category>
  <size>
   L
  </size>
  <color>
   Голубой
  </color>
  <material>
   Полиэстер
  </material>
  <price>
   247004
  </price>
  <rating>
   2.43
  </rating>
  <reviews>
   694459
  </reviews>
  <exclusive>
   no
  </exclusive>
  <sporty>
   yes
  </sporty>
 </clothing>
 <clothing>
  <id>
   916111036
  </id>
  <name>
   Reebok Pants F-3238
  </name>
  <category>
   Pants
  </category>
  <size>
   S
  </size>
  <color>
   Красный
  </color>
  <material>
   Шерсть
  </material>
  <price>
   429264
  </price>
  <rating>
   3.96
  </rating>
  <reviews>
   150186
  </reviews>
  <new>
   +
  </new>
  <exclusive>
   yes
  </exclusive>
  <sporty>
   no
  </sporty>
 </clothing>
 <clothing>
  <id>
   189420598
  </id>
  <name>
   Asics T-shirt T-8453
  </name>
  <category>
   T-shirt
  </category>
  <size>
   S
  </size>
  <color>
   Желтый
  </color>
  <material>
   Вискоза
  </material>
  <price>
   817755
  </price>
  <rating>
   2.2
  </rating>
  <reviews>
   123132
  </reviews>
  <exclusive>
   no
  </exclusive>
 </clothing>
 <clothing>
  <id>
   254280786
  </id>
  <name>
   Reebok Hat H-6158
  </name>
  <category>
   Hat
  </category>
  <size>
   XXL
  </size>
  <color>
   Голубой
  </color>
  <material>
   Нейлон
  </material>
  <price>
   430266
  </price>
  <rating>
   2.67
  </rating>
  <reviews>
   685359
  </reviews>
  <new>
   +
  </new>
  <exclusive>
   yes
  </exclusive>
 </clothing>
 <clothing>
  <id>
   913084403
  </id>
  <name>
   Reebok Skirt H-3302
  </name>
  <category>
   Skirt
  </category>
  <size>
   XXL
  </size>
  <color>
   Синий
  </color>
  <material>
   Вискоза
  </material>
  <price>
   585128
  </price>
  <rating>
   1.24
  </rating>
  <reviews>
   78435
  </reviews>
  <exclusive>
   no
  </exclusive>
 </clothing>
 <clothing>
  <id>
   867646264
  </id>
  <name>
   Ellesse Hat O-1435
  </name>
  <category>
   Hat
  </category>
  <size>
   XL
  </size>
  <color>
   Голубой
  </color>
  <material>
   Нейлон
  </material>
  <price>
   842402
  </price>
  <rating>
   3.47
  </rating>
  <reviews>
   643429
  </reviews>
  <new>
   -
  </new>
  <exclusive>
   yes
  </exclusive>
 </clothing>
 <clothing>
  <id>
   801255896
  </id>
  <name>
   Converse Shirt P-2136
  </name>
  <category>
   Shirt
  </category>
  <size>
   XL
  </size>
  <color>
   Фиолетовый
  </color>
  <material>
   Нейлон
  </material>
  <price>
   788590
  </price>
  <rating>
   3.23
  </rating>
  <reviews>
   42993
  </reviews>
  <new>
   +
  </new>
  <exclusive>
   no
  </exclusive>
 </clothing>
 <clothing>
  <id>
   110224237
  </id>
  <name>
   Brooks Umbrellas M-7006
  </name>
  <category>
   Umbrellas
  </category>
  <size>
   L
  </size>
  <color>
   Фиолетовый
  </color>
  <material>
   Шелк
  </material>
  <price>
   897953
  </price>
  <rating>
   3.21
  </rating>
  <reviews>
   184410
  </reviews>
  <new>
   +
  </new>
  <exclusive>
   no
  </exclusive>
  <sporty>
   no
  </sporty>
 </clothing>
 <clothing>
  <id>
   513413150
  </id>
  <name>
   Asics Hat X-4084
  </name>
  <category>
   Hat
  </category>
  <size>
   S
  </size>
  <color>
   Зеленый
  </color>
  <material>
   Полиэстер
  </material>
  <price>
   289568
  </price>
  <rating>
   2.26
  </rating>
  <reviews>
   503772
  </reviews>
 </clothing>
 <clothing>
  <id>
   134796946
  </id>
  <name>
   Lacoste T-shirt K-6850
  </name>
  <category>
   T-shirt
  </category>
  <size>
   L
  </size>
  <color>
   Фиолетовый
  </color>
  <material>
   Нейлон
  </material>
  <price>
   264378
  </price>
  <rating>
   2.71
  </rating>
  <reviews>
   312544
  </reviews>
  <new>
   +
  </new>
 </clothing>
 <clothing>
  <id>
   900316786
  </id>
  <name>
   Nike Hat B-1490
  </name>
  <category>
   Hat
  </category>
  <size>
   XL
  </size>
  <color>
   Красный
  </color>
  <material>
   Полиэстер
  </material>
  <price>
   313528
  </price>
  <rating>
   4.04
  </rating>
  <reviews>
   409085
  </reviews>
 </clothing>
 <clothing>
  <id>
   745435143
  </id>
  <name>
   Addidas Hat V-3490
  </name>
  <category>
   Hat
  </category>
  <size>
   L
  </size>
  <color>
   Красный
  </color>
  <material>
   Кожа
  </material>
  <price>
   624611
  </price>
  <rating>
   2.66
  </rating>
  <reviews>
   34076
  </reviews>
  <exclusive>
   yes
  </exclusive>
  <sporty>
   no
  </sporty>
 </clothing>
</clothing-items>
